.coveralls.yml
.gitignore
.travis.yml
LICENSE
MANIFEST.in
README.rst
TODO
khayyam-travis-gh-pages.enc
release.sh
requirement.txt
setup.cfg
setup.py
travis-gh-pages.sh
win-release.bat
Khayyam_jalali.egg-info/PKG-INFO
Khayyam_jalali.egg-info/SOURCES.txt
Khayyam_jalali.egg-info/dependency_links.txt
Khayyam_jalali.egg-info/requires.txt
Khayyam_jalali.egg-info/top_level.txt
Khayyam_jalali.egg-info/zip-safe
khayyam/__init__.py
khayyam/algorithms.py
khayyam/algorithms_c.c
khayyam/algorithms_pure.py
khayyam/compat.py
khayyam/constants.py
khayyam/helpers.py
khayyam/jalali_date.py
khayyam/jalali_datetime.py
khayyam/timezones.py
khayyam/formatting/__init__.py
khayyam/formatting/constants.py
khayyam/formatting/formatters.py
khayyam/formatting/directives/__init__.py
khayyam/formatting/directives/ampm.py
khayyam/formatting/directives/base.py
khayyam/formatting/directives/day.py
khayyam/formatting/directives/month.py
khayyam/formatting/directives/persian.py
khayyam/formatting/directives/time.py
khayyam/formatting/directives/tz.py
khayyam/formatting/directives/year.py
khayyam/tests/__init__.py
khayyam/tests/test_algorithms.py
khayyam/tests/test_jalali_date.py
khayyam/tests/test_jalali_date_formatter.py
khayyam/tests/test_jalali_datetime.py
khayyam/tests/test_jalali_datetime_formatter.py
khayyam/tests/test_timezone.py
sphinx/Makefile
sphinx/api.rst
sphinx/conf.py
sphinx/development.rst
sphinx/directives.rst
sphinx/find_intersphinx_link.py
sphinx/index.rst
sphinx/installation.rst
sphinx/intro.rst
sphinx/make.bat
sphinx/migration.rst
sphinx/persiancalendar.rst
sphinx/watch
sphinx/_static/.keep
sphinx/_static/favicon.ico
sphinx/_templates/.keep