Metadata-Version: 2.1
Name: Khayyam-jalali
Version: 3.0.20
Summary: Persian Date & Time library (aka: Jalali Calendar) with timezone, DST(daylight-saving), full formatting & parsing support for python 2 & 3 including c extention
Home-page: http://khayyam.dobisel.com
Author: ['Vahid Mardani', 'sayeh kargari']
Author-email: ['vahid.mardani@gmail.com', 'sayeh.kargari31@gmail.com']
License: GPLv3
Keywords: Khayyam persian jalali date time datetime conversion
Classifier: Programming Language :: Python
Classifier: Development Status :: 5 - Production/Stable
Classifier: License :: OSI Approved :: GNU General Public License v3 (GPLv3)
Classifier: Operating System :: OS Independent
Classifier: Programming Language :: Python
Classifier: Programming Language :: Python :: 2.7
Classifier: Programming Language :: Python :: 3.3
Classifier: Programming Language :: Python :: 3.4
Classifier: Programming Language :: Python :: 3.5
Classifier: Intended Audience :: Developers
Classifier: Natural Language :: English
Classifier: Natural Language :: Persian
Classifier: Topic :: Software Development :: Libraries :: Python Modules
Classifier: Topic :: Software Development :: Localization
License-File: LICENSE
Requires-Dist: rtl
Requires-Dist: sphinx
Requires-Dist: coverage
Requires-Dist: coveralls
Requires-Dist: nose-pudb
Requires-Dist: persiantools
